mase_triton/__init__.py
mase_triton/about.py
mase_triton/dtype.py
mase_triton/logging.py
mase_triton/manager.py
mase_triton/_mxfp_simple/fake.py
mase_triton/_mxfp_simple/helpers.py
mase_triton/_mxfp_simple/layers.py
mase_triton/_mxfp_simple/meta.py
mase_triton/_mxfp_simple/utils.py
mase_triton/_mxfp_simple/functional/__init__.py
mase_triton/_mxfp_simple/functional/cast.py
mase_triton/_mxfp_simple/functional/linear.py
mase_triton/_mxfp_simple/functional/matmul.py
mase_triton/_mxfp_simple/kernels/__init__.py
mase_triton/_mxfp_simple/kernels/cast.py
mase_triton/minifloat/__init__.py
mase_triton/minifloat/fake.py
mase_triton/minifloat/layers.py
mase_triton/minifloat/meta.py
mase_triton/minifloat/functional/__init__.py
mase_triton/minifloat/functional/cast.py
mase_triton/minifloat/functional/linear.py
mase_triton/minifloat/functional/matmul.py
mase_triton/minifloat/kernels/__init__.py
mase_triton/minifloat/kernels/cast.py
mase_triton/mxfp/fake.py
mase_triton/mxfp/helpers.py
mase_triton/mxfp/layers.py
mase_triton/mxfp/meta.py
mase_triton/mxfp/functional/__init__.py
mase_triton/mxfp/functional/cast.py
mase_triton/mxfp/functional/linear.py
mase_triton/mxfp/functional/matmul.py
mase_triton/mxfp/kernels/__init__.py
mase_triton/mxfp/kernels/cast.py
mase_triton/optical_compute/__init__.py
mase_triton/optical_compute/functional.py
mase_triton/optical_compute/layers.py
mase_triton/optical_compute/core/__init__.py
mase_triton/optical_compute/core/optical_transformer/__init__.py
mase_triton/optical_compute/core/optical_transformer/fake.py
mase_triton/optical_compute/core/optical_transformer/linear.py
mase_triton/optical_compute/core/optical_transformer/matmul.py
mase_triton/optical_compute/core/optical_transformer/quantize.py
mase_triton/optical_compute/core/optical_transformer/utils.py
mase_triton/random_bitflip/__init__.py
mase_triton/random_bitflip/core.py
mase_triton/random_bitflip/functional.py
mase_triton/random_bitflip/layers.py
mase_triton/random_bitflip/utils.py
mase_triton-0.0.6.post4.dist-info/METADATA
mase_triton-0.0.6.post4.dist-info/WHEEL
mase_triton-0.0.6.post4.dist-info/RECORD
