Metadata-Version: 2.4
Name: mase-triton
Version: 0.0.6.post4
Summary: Triton kernels for MASE
Project-URL: Repository, https://github.com/DeepWok/mase-triton.git
Author-email: Cheng Zhang <chengzhang98@outlook.com>
Maintainer-email: Cheng Zhang <chengzhang98@outlook.com>
License-Expression: Apache-2.0
Keywords: deep-learning,mase,triton
Requires-Python: >=3.11
Requires-Dist: colorlog>=6.9.0
Requires-Dist: numpy
Requires-Dist: torch>=2.6.0
Requires-Dist: triton>=2.6.0
